orcestra/__init__.py
orcestra/data/worldfirs.json
orcestra/flight_performance.py
orcestra/flightplan.py
orcestra/io.py
orcestra/ipfs.py
orcestra/meteor.py
orcestra/postprocess/__init__.py
orcestra/postprocess/config.json
orcestra/postprocess/level0.py
orcestra/postprocess/level1.py
orcestra/sat.py
orcestra/tools.py
orcestra/utils.py
orcestra/weathermaps.py
orcestra-0.0.30.dist-info/METADATA
orcestra-0.0.30.dist-info/WHEEL
orcestra-0.0.30.dist-info/entry_points.txt
orcestra-0.0.30.dist-info/licenses/LICENSE
orcestra-0.0.30.dist-info/RECORD
